{
    "Fruit Yogurt Parfait": [
        "Vegetarian",
        "Contains Milk",
        "Contains Wheat"
    ],
    "Hot Cereal Breakfast Toppings": [
        "Vegetarian",
        "Contains Wheat"
    ],
    "Oatmeal": [
        "Vegan",
        "Vegetarian",
        "Gluten Free",
        "Contains Wheat"
    ],
    "Bacon": [
        "Gluten Free"
    ],
    "Just Egg Plant Based Scramble": [
        "Vegan",
        "Vegetarian",
        "Gluten Free",
        "Contains Soybeans"
    ],
    "Karana Vegan Sausage Patty": [
        "Vegan",
        "Vegetarian",
        "Gluten Free"
    ],
    "Scrambled Eggs": [
        "Vegetarian",
        "Gluten Free",
        "Contains Eggs"
    ],
    "Triangle Hasbrown": [
        "Vegan",
        "Vegetarian",
        "Gluten Free",
        "Contains Soybeans"
    ],
    "Turkey Sausage Patty": [
        "Gluten Free",
        "Contains Soybeans"
    ],
    "Biscuits & Country Sausage Gravy": [
        "Contains Milk",
        "Contains Wheat"
    ],
    "Assorted Bagels": [
        "Contains Wheat"
    ],
    "Cinnamon Roll": [
        "Contains Milk",
        "Contains Eggs",
        "Contains Wheat",
        "Contains Soybeans"
    ],
    "Vegan Lemon Glaze Muffin": [
        "Vegan",
        "Vegetarian",
        "Contains Wheat"
    ],
    "Apple Cranberry Salad": [
        "Vegetarian",
        "Contains Milk"
    ],
    "Buffalo Cauliflower Wrap": [
        "Vegan",
        "Vegetarian",
        "Contains Wheat",
        "Contains Soybeans"
    ],
    "Fresh Seasonal Fruits & Vegetables": [
        "Vegetarian",
        "Contains Milk",
        "Contains Eggs",
        "Contains Fish",
        "Contains Crustacean Shellfish",
        "Contains Tree Nuts",
        "Contains Peanuts",
        "Contains Wheat",
        "Contains Soybeans",
        "Contains Sesame"
    ],
    "Halal Grilled Chicken Breast": [
        "Gluten Free"
    ],
    "Chicken Tortilla Soup": [],
    "Rice and Vegetable Soup": [
        "Vegan",
        "Vegetarian",
        "Gluten Free",
        "Contains Soybeans"
    ],
    "Chow Fun Noodles": [
        "Contains Crustacean Shellfish",
        "Contains Wheat",
        "Contains Soybeans"
    ],
    "Halal Chicken Chow Fun Noodles": [
        "Contains Crustacean Shellfish",
        "Contains Wheat",
        "Contains Soybeans"
    ],
    "Pita Bar with Hummus, Olives, Red Peppers, & Artichoke Heart": [
        "Vegetarian",
        "Contains Milk",
        "Contains Wheat",
        "Contains Soybeans",
        "Contains Sesame"
    ],
    "Garlic French Bread": [
        "Vegetarian",
        "Contains Milk",
        "Contains Wheat",
        "Contains Soybeans"
    ],
    "Italian Sausage and Peppers with Pasta": [
        "Contains Wheat"
    ],
    "Tempeh Bolognaise Sauce": [
        "Vegan",
        "Vegetarian",
        "Gluten Free",
        "Contains Soybeans"
    ],
    "BBQ Beans": [],
    "Macaroni Salad": [
        "Vegan",
        "Vegetarian",
        "Contains Wheat",
        "Contains Soybeans"
    ],
    "Mesquite Smoked Beef Brisket": [],
    "Roasted Carrots": [
        "Vegan",
        "Vegetarian",
        "Gluten Free"
    ],
    "Fresh Baked Assorted Cookies": [
        "Contains Milk",
        "Contains Eggs",
        "Contains Tree Nuts",
        "Contains Peanuts",
        "Contains Wheat",
        "Contains Soybeans"
    ],
    "Orange Creamsicle Jello": [
        "Contains Milk"
    ],
    "S'More Brownie": [
        "Contains Milk",
        "Contains Eggs",
        "Contains Wheat",
        "Contains Soybeans"
    ],
    "Sugar Free Berry Jello": [],
    "Vegan Peanut Butter Cookies": [
        "Vegan",
        "Vegetarian",
        "Contains Peanuts",
        "Contains Wheat"
    ],
    "Braised Chick Peas": [
        "Vegan",
        "Vegetarian",
        "Gluten Free"
    ],
    "Cooked Farro": [
        "Vegan",
        "Vegetarian",
        "Contains Wheat"
    ],
    "Oven Roasted Broccoli & Cauliflower": [
        "Vegan",
        "Vegetarian",
        "Gluten Free"
    ],
    "Vegan Beef Fajitas - Lettuce Wrap": [
        "Vegan",
        "Vegetarian",
        "Contains Wheat",
        "Contains Soybeans"
    ],
    "Brown Rice": [
        "Vegan",
        "Vegetarian",
        "Gluten Free"
    ],
    "Halal Teriyaki Chicken": [
        "Contains Soybeans",
        "Contains Sesame"
    ],
    "Jasmine Rice": [
        "Vegan",
        "Vegetarian",
        "Gluten Free"
    ],
    "Plant Based Teriyaki Chicken": [
        "Vegan",
        "Vegetarian",
        "Contains Wheat",
        "Contains Soybeans",
        "Contains Sesame"
    ],
    "Cuban Slider": [
        "Contains Milk",
        "Contains Wheat",
        "Contains Soybeans"
    ],
    "Curly Fries": [
        "Vegan",
        "Vegetarian",
        "Gluten Free"
    ],
    "Vegan Grilled Cheese": [
        "Vegan",
        "Vegetarian",
        "Contains Wheat",
        "Contains Soybeans"
    ],
    "Baked Potato Bar": [
        "Vegetarian",
        "Gluten Free",
        "Contains Milk"
    ],
    "Baked Potato": [
        "Vegan",
        "Vegetarian",
        "Gluten Free"
    ],
    "Barn Smokehouse Vegan Chili": [
        "Vegan",
        "Vegetarian",
        "Gluten Free",
        "Contains Soybeans"
    ],
    "Texas Beef Chili": [
        "Gluten Free",
        "Contains Milk"
    ],
    "Red Velvet Whoopie Pie": [
        "Vegetarian",
        "Contains Milk",
        "Contains Eggs",
        "Contains Wheat",
        "Contains Soybeans"
    ],
    "Vegan Mocha Cupcake": [
        "Contains Wheat",
        "Contains Soybeans"
    ],
    "Sausage Links": [
        "Gluten Free"
    ],
    "Scrambled  Eggs w/ Cheese": [
        "Vegetarian",
        "Gluten Free",
        "Contains Milk",
        "Contains Eggs"
    ],
    "Breakfast Burritos": [
        "Vegetarian",
        "Contains Milk",
        "Contains Eggs",
        "Contains Wheat"
    ],
    "Old Fashioned Coffee Cake": [
        "Vegetarian",
        "Contains Milk",
        "Contains Eggs",
        "Contains Wheat",
        "Contains Soybeans"
    ],
    "Vegan Overnight Oats": [
        "Vegan",
        "Vegetarian",
        "Gluten Free"
    ],
    "Fire Cracker Chicken": [
        "Contains Wheat",
        "Contains Soybeans"
    ],
    "Fire Cracker Tofu": [
        "Vegan",
        "Vegetarian",
        "Contains Soybeans"
    ],
    "French Bread Sausage Pizza": [
        "Contains Milk",
        "Contains Wheat"
    ],
    "Margherita French Bread Pizza": [
        "Vegetarian",
        "Contains Milk",
        "Contains Wheat"
    ],
    "Vegan Cheese Pizza": [
        "Vegan",
        "Vegetarian",
        "Contains Tree Nuts",
        "Contains Wheat",
        "Contains Soybeans"
    ],
    "Cavatappi Pomodoro Primavera": [
        "Vegan",
        "Vegetarian",
        "Contains Wheat"
    ],
    "Garlic Bread Sticks": [
        "Vegetarian",
        "Contains Milk",
        "Contains Wheat"
    ],
    "Oven Roasted Cauliflower": [
        "Vegan",
        "Vegetarian",
        "Gluten Free"
    ],
    "Halal Beef Picadillo Burrito": [
        "Contains Wheat"
    ],
    "Refried Beans": [
        "Vegan",
        "Vegetarian",
        "Gluten Free"
    ],
    "Roasted Vegetables": [
        "Vegan",
        "Vegetarian",
        "Gluten Free"
    ],
    "Salsa Bar": [
        "Vegetarian",
        "Gluten Free",
        "Contains Milk"
    ],
    "Spanish Rice": [
        "Gluten Free"
    ],
    "Lime Jello": [],
    "Raspberry Streusel": [
        "Vegetarian",
        "Contains Milk",
        "Contains Eggs",
        "Contains Wheat",
        "Contains Soybeans"
    ],
    "Sugar Free Citrus Jello": [],
    "Vegan Snickerdoodle Cookies": [
        "Vegan",
        "Vegetarian",
        "Contains Wheat",
        "Contains Soybeans"
    ],
    "Maple Sweet Potatoes": [
        "Vegan",
        "Vegetarian",
        "Gluten Free"
    ],
    "Red Quinoa": [
        "Vegetarian",
        "Gluten Free"
    ],
    "Roasted Brussels Sprouts": [
        "Vegan",
        "Vegetarian",
        "Gluten Free"
    ],
    "Smoked Soy Chicken Bowl Hickory Barbeque Sauce": [
        "Vegan",
        "Contains Wheat",
        "Contains Soybeans"
    ],
    "Shanghai Shrimp Udon": [
        "Contains Crustacean Shellfish",
        "Contains Wheat",
        "Contains Soybeans",
        "Contains Sesame"
    ],
    "Shanghai Vegetable Udon": [
        "Contains Wheat",
        "Contains Soybeans",
        "Contains Sesame"
    ],
    "Shoestring Fries": [
        "Vegan",
        "Vegetarian",
        "Gluten Free"
    ],
    "Texas Grilled Cheese": [
        "Vegetarian",
        "Contains Milk",
        "Contains Wheat",
        "Contains Soybeans"
    ],
    "Huli Huli Chicken": [
        "Contains Wheat",
        "Contains Soybeans",
        "Contains Sesame"
    ],
    "Roasted Summer Squash": [
        "Vegan",
        "Vegetarian",
        "Gluten Free"
    ],
    "Chocolate Sheet Cake": [
        "Vegetarian",
        "Contains Milk",
        "Contains Eggs",
        "Contains Wheat",
        "Contains Soybeans"
    ],
    "Vegan Lemon Cookie": [
        "Vegan",
        "Vegetarian",
        "Contains Wheat",
        "Contains Soybeans"
    ],
    "Sausage Patty": [
        "Gluten Free"
    ],
    "Tater Tots": [
        "Vegan",
        "Vegetarian",
        "Gluten Free"
    ],
    "French Toast Sticks": [
        "Vegetarian",
        "Contains Wheat",
        "Contains Soybeans"
    ],
    "Double Chocolate Coffee Cake": [
        "Vegetarian",
        "Contains Milk",
        "Contains Eggs",
        "Contains Wheat",
        "Contains Soybeans"
    ],
    "Vegan Strawberry Muffin": [
        "Vegan",
        "Vegetarian",
        "Contains Wheat"
    ],
    "Peanut Thai Tofu Wrap": [
        "Vegan",
        "Vegetarian",
        "Contains Peanuts",
        "Contains Wheat",
        "Contains Soybeans",
        "Contains Sesame"
    ],
    "New England Clam Chowder": [
        "Contains Milk",
        "Contains Fish",
        "Contains Crustacean Shellfish",
        "Contains Soybeans"
    ],
    "Tomato Bisque Soup": [
        "Vegetarian",
        "Gluten Free",
        "Contains Milk"
    ],
    "Korean Bbq Pork Banh Mi": [
        "Contains Milk",
        "Contains Eggs",
        "Contains Fish",
        "Contains Wheat",
        "Contains Soybeans",
        "Contains Sesame"
    ],
    "Tofu Banh Mi": [
        "Contains Eggs",
        "Contains Fish",
        "Contains Wheat",
        "Contains Soybeans"
    ],
    "Classic Pepperoni Pizza": [
        "Contains Milk",
        "Contains Wheat",
        "Contains Soybeans"
    ],
    "Vegan Veggie Supreme Pizza": [
        "Vegan",
        "Vegetarian",
        "Contains Tree Nuts",
        "Contains Wheat",
        "Contains Soybeans"
    ],
    "Vegetarian Supreme Pizza": [
        "Vegetarian",
        "Contains Milk",
        "Contains Wheat",
        "Contains Soybeans"
    ],
    "Chicken Shawarma Slider": [
        "Contains Milk",
        "Contains Wheat",
        "Contains Sesame"
    ],
    "Steamed Carrots": [
        "Vegan",
        "Vegetarian",
        "Gluten Free"
    ],
    "Cilantro Lime Rice": [
        "Vegan",
        "Vegetarian",
        "Gluten Free"
    ],
    "Roasted Zucchini": [
        "Vegan",
        "Vegetarian",
        "Gluten Free"
    ],
    "Salmon Charmoula": [
        "Gluten Free",
        "Contains Fish"
    ],
    "Sugar Cookie Bar": [
        "Vegetarian",
        "Contains Milk",
        "Contains Eggs",
        "Contains Wheat",
        "Contains Soybeans"
    ],
    "Vanilla Pudding": [
        "Contains Milk"
    ],
    "Vegan Chocolate Cupcake": [
        "Contains Wheat",
        "Contains Soybeans"
    ],
    "Cucumbers & Red Onions": [],
    "Tomato Chutney": [
        "Vegan",
        "Vegetarian",
        "Gluten Free"
    ],
    "Vegetable Pakoras": [
        "Vegan",
        "Vegetarian",
        "Gluten Free"
    ],
    "Orange Chicken": [
        "Contains Wheat",
        "Contains Soybeans"
    ],
    "Orange Crispy Tofu": [
        "Vegan",
        "Vegetarian",
        "Contains Soybeans"
    ],
    "Nashville Chicken Mac & Cheese Bowl": [
        "Contains Milk",
        "Contains Wheat"
    ],
    "Peas, Carrots & Corn with Caramelized Onions": [
        "Vegan",
        "Vegetarian",
        "Gluten Free"
    ],
    "Blackened Tilapia": [
        "Contains Fish",
        "Contains Wheat"
    ],
    "Collard Greens": [
        "Vegan",
        "Vegetarian",
        "Gluten Free"
    ],
    "Dirty Rice": [
        "Gluten Free"
    ],
    "Classic Cheesecake": [
        "Contains Milk",
        "Contains Eggs",
        "Contains Wheat",
        "Contains Soybeans"
    ],
    "Vegan Cranberry Bar": [
        "Vegan",
        "Vegetarian",
        "Contains Wheat",
        "Contains Soybeans"
    ],
    "Alu Chole": [
        "Vegan",
        "Vegetarian",
        "Gluten Free"
    ],
    "Green Chutney": [
        "Vegan",
        "Vegetarian",
        "Gluten Free"
    ],
    "Self Serv Waffle": [
        "Vegetarian",
        "Contains Milk",
        "Contains Wheat"
    ],
    "Egg Omelets Made to Order": [
        "Vegetarian",
        "Gluten Free",
        "Contains Eggs"
    ],
    "Eggs Made to Order - Over Easy, Med or Well": [
        "Vegetarian",
        "Gluten Free",
        "Contains Eggs"
    ],
    "Omelet Bar Toppings": [
        "Gluten Free",
        "Contains Milk"
    ],
    "Cherry Turnover": [
        "Contains Wheat"
    ],
    "Vegan Chocolate Chip Muffin": [
        "Vegan",
        "Vegetarian",
        "Contains Milk",
        "Contains Wheat"
    ],
    "Vegetable Minestrone Soup": [
        "Vegan",
        "Vegetarian",
        "Contains Eggs",
        "Contains Wheat"
    ],
    "French Bread Pepperoni Pizza": [
        "Contains Milk",
        "Contains Wheat"
    ],
    "Three Cheese French Bread Pizza": [
        "Vegetarian",
        "Contains Milk",
        "Contains Wheat"
    ],
    "Buffalo Ranch Chicken Slider": [
        "Contains Milk",
        "Contains Wheat",
        "Contains Soybeans"
    ],
    "House-made BBQ Potato Chips": [
        "Vegan",
        "Vegetarian",
        "Gluten Free"
    ],
    "Basmati Rice": [
        "Vegan",
        "Vegetarian",
        "Gluten Free"
    ],
    "Falafel": [
        "Vegan",
        "Vegetarian",
        "Contains Wheat",
        "Contains Soybeans"
    ],
    "Halal Chicken Sharwarma": [
        "Gluten Free"
    ],
    "Pita Condiments (Tomato, Cucumbers & Red Onions)": [
        "Vegan",
        "Vegetarian",
        "Gluten Free"
    ],
    "Vegan Naan Bread": [
        "Vegan",
        "Vegetarian",
        "Contains Wheat",
        "Contains Soybeans",
        "Contains Sesame"
    ],
    "Strawberry Jello": [],
    "Vegan Cookie Dough Brownie": [
        "Vegan",
        "Vegetarian",
        "Contains Milk",
        "Contains Wheat",
        "Contains Soybeans"
    ],
    "Vegan Nacho Bar": [
        "Gluten Free",
        "Contains Soybeans"
    ],
    "Shrimp Dan Dan Noodle": [
        "Contains Crustacean Shellfish",
        "Contains Wheat",
        "Contains Soybeans",
        "Contains Sesame"
    ],
    "Tofu Dan Dan Noodle": [
        "Vegan",
        "Vegetarian",
        "Contains Wheat",
        "Contains Soybeans",
        "Contains Sesame"
    ],
    "Broccoli &Cranberry Salad": [
        "Vegetarian",
        "Gluten Free",
        "Contains Eggs",
        "Contains Tree Nuts",
        "Contains Peanuts"
    ],
    "Grilled Chicken Club Sandwich": [
        "Contains Milk",
        "Contains Wheat",
        "Contains Soybeans"
    ],
    "Herb Pan Gravy": [
        "Contains Milk",
        "Contains Wheat",
        "Contains Soybeans"
    ],
    "Homestyle Fried Chicken": [
        "Contains Wheat"
    ],
    "Roasted Garlic Mashed Potatoes": [
        "Vegetarian",
        "Gluten Free",
        "Contains Milk"
    ],
    "Cannoli": [
        "Vegetarian",
        "Contains Milk",
        "Contains Eggs",
        "Contains Wheat",
        "Contains Soybeans"
    ],
    "Vegan Chocolate Cookies": [
        "Vegan",
        "Vegetarian",
        "Contains Milk",
        "Contains Wheat",
        "Contains Soybeans"
    ],
    "Blueberry Muffin": [
        "Vegetarian",
        "Contains Milk",
        "Contains Eggs",
        "Contains Wheat",
        "Contains Soybeans"
    ],
    "Vegan Cinnamon Roll": [
        "Vegan",
        "Vegetarian",
        "Contains Wheat",
        "Contains Soybeans"
    ],
    "Mozzarella Flat Bread Pizza": [
        "Vegetarian",
        "Contains Milk",
        "Contains Wheat",
        "Contains Soybeans"
    ],
    "Southwestern Cheesesteak Sandwich": [
        "Contains Milk",
        "Contains Eggs",
        "Contains Wheat",
        "Contains Soybeans"
    ],
    "Vegan Chipotle Potato Salad": [
        "Vegan",
        "Vegetarian",
        "Gluten Free",
        "Contains Soybeans"
    ],
    "Vegetarian Philly Sandwich": [
        "Contains Milk",
        "Contains Eggs",
        "Contains Wheat",
        "Contains Soybeans"
    ],
    "Herb Whole Roasted Halal Chicken": [
        "Gluten Free"
    ],
    "Roasted Potatoes": [
        "Vegan",
        "Vegetarian",
        "Gluten Free"
    ],
    "Steamed Zucchini": [
        "Vegan",
        "Vegetarian",
        "Gluten Free"
    ],
    "Coffee Pudding": [
        "Contains Milk"
    ],
    "Vegan Walnut Brownie": [
        "Vegan",
        "Vegetarian",
        "Contains Tree Nuts",
        "Contains Wheat",
        "Contains Soybeans"
    ],
    "Plant Based Beef & Broccoli": [
        "Contains Wheat",
        "Contains Soybeans",
        "Contains Sesame"
    ],
    "BBQ Ranch Chicken Flat Bread Pizza": [
        "Contains Milk",
        "Contains Eggs",
        "Contains Wheat",
        "Contains Soybeans"
    ],
    "BBQ Ranch Soy Chicken Flat Bread Pizza": [
        "Vegetarian",
        "Contains Milk",
        "Contains Eggs",
        "Contains Wheat",
        "Contains Soybeans"
    ],
    "Ensenada Beans": [
        "Vegan",
        "Vegetarian",
        "Gluten Free"
    ],
    "Green Chilaquiles": [
        "Vegetarian",
        "Gluten Free",
        "Contains Milk"
    ],
    "Pork Chile Verde": [],
    "Vegetarian Soy Chicken Fajita": [
        "Vegan",
        "Vegetarian",
        "Contains Wheat",
        "Contains Soybeans"
    ],
    "BBQ Chicken Thighs": [
        "Gluten Free"
    ],
    "Corn Maque Choux": [
        "Vegetarian",
        "Gluten Free",
        "Contains Milk"
    ],
    "Mashed Potatoes": [
        "Vegetarian",
        "Gluten Free",
        "Contains Milk"
    ],
    "Coconut Cream Pie": [
        "Vegetarian",
        "Contains Milk",
        "Contains Eggs",
        "Contains Wheat",
        "Contains Soybeans"
    ],
    "Vegan Vanilla Cupcake": [
        "Vegan",
        "Vegetarian",
        "Contains Wheat",
        "Contains Soybeans"
    ],
    "Home Fries": [
        "Vegan",
        "Vegetarian",
        "Gluten Free"
    ],
    "Strawberry Pancakes": [
        "Vegetarian",
        "Contains Milk",
        "Contains Eggs",
        "Contains Wheat",
        "Contains Soybeans"
    ],
    "Caramel Apple Coffee cake": [
        "Contains Milk",
        "Contains Eggs",
        "Contains Wheat",
        "Contains Soybeans"
    ],
    "Vegan Scone": [
        "Contains Tree Nuts",
        "Contains Wheat",
        "Contains Soybeans"
    ],
    "Farro and Squash Salad": [
        "Vegetarian",
        "Contains Wheat"
    ],
    "Soybean Hummus Wrap": [
        "Vegan",
        "Vegetarian",
        "Contains Wheat",
        "Contains Soybeans",
        "Contains Sesame"
    ],
    "Corn Chowder Soup": [
        "Vegetarian",
        "Contains Milk",
        "Contains Wheat"
    ],
    "Butter Cauliflower & Chickpeas": [
        "Vegan",
        "Vegetarian",
        "Gluten Free",
        "Contains Milk"
    ],
    "Butter Chicken": [
        "Gluten Free",
        "Contains Milk"
    ],
    "Three Cheese Pizza": [
        "Vegetarian",
        "Contains Milk",
        "Contains Wheat",
        "Contains Soybeans"
    ],
    "Southwestern Corn Salad": [
        "Vegan",
        "Vegetarian",
        "Gluten Free"
    ],
    "Spicy Crispy Chicken Slider": [
        "Contains Milk",
        "Contains Wheat"
    ],
    "Corn Bread": [
        "Vegetarian",
        "Contains Milk",
        "Contains Eggs",
        "Contains Wheat"
    ],
    "Pepper Jack O' Gratin Potatoes": [
        "Vegetarian",
        "Gluten Free",
        "Contains Milk"
    ],
    "Smoke House Halal Chicken": [
        "Gluten Free"
    ],
    "Chocolate Mousse": [
        "Vegetarian",
        "Gluten Free",
        "Contains Milk",
        "Contains Soybeans"
    ],
    "Raspberry Fudge Brownies": [
        "Contains Milk",
        "Contains Eggs",
        "Contains Wheat",
        "Contains Soybeans"
    ],
    "Vegan Orange Sugar Cookies": [
        "Vegan",
        "Vegetarian",
        "Contains Wheat",
        "Contains Soybeans"
    ],
    "Steamed Broccoli": [
        "Vegan",
        "Vegetarian",
        "Gluten Free"
    ],
    "Tamarind Chutney": [
        "Vegan",
        "Vegetarian",
        "Gluten Free"
    ],
    "General Tso Chicken": [
        "Contains Wheat",
        "Contains Soybeans",
        "Contains Sesame"
    ],
    "Tofu with Black Bean Sauce": [
        "Vegan",
        "Vegetarian",
        "Contains Wheat",
        "Contains Soybeans",
        "Contains Sesame"
    ],
    "Rigatoni Pasta and Peppers with Marinara Sauce": [
        "Contains Wheat"
    ],
    "Philly Chessesteak Slider": [
        "Contains Milk",
        "Contains Wheat",
        "Contains Soybeans"
    ],
    "Tacos Al Pastor (Pork)": [
        "Gluten Free"
    ],
    "Salted Caramel Cupcake": [
        "Contains Milk",
        "Contains Eggs",
        "Contains Wheat",
        "Contains Soybeans"
    ],
    "Vegan Strawberry Cookies": [
        "Vegan",
        "Vegetarian",
        "Contains Wheat",
        "Contains Soybeans"
    ],
    "Vegan Banana Muffins": [
        "Vegan",
        "Vegetarian",
        "Contains Wheat",
        "Contains Soybeans"
    ],
    "Halal Chicken Chow Mein": [
        "Contains Wheat",
        "Contains Soybeans",
        "Contains Sesame"
    ],
    "Vegetable Chow Mein": [
        "Vegetarian",
        "Contains Wheat",
        "Contains Soybeans",
        "Contains Sesame"
    ],
    "Hand Crafted Italian Cheese Pizza": [
        "Vegetarian",
        "Contains Milk",
        "Contains Wheat",
        "Contains Soybeans"
    ],
    "Hand Crafted Italian Chicken Bacon Ranch Pizza": [
        "Contains Milk",
        "Contains Eggs",
        "Contains Wheat",
        "Contains Soybeans"
    ],
    "Chicken Taquitos": [
        "Contains Milk",
        "Contains Wheat",
        "Contains Soybeans"
    ],
    "BBQ Pork Baked Beans": [],
    "Carrots and Corn": [
        "Vegan",
        "Vegetarian",
        "Gluten Free"
    ],
    "Fresh Baked Buttermilk Biscuit": [
        "Vegetarian",
        "Contains Milk",
        "Contains Wheat"
    ],
    "Kansas City Barbecue Pork": [
        "Gluten Free"
    ],
    "Cocoa Puff Krispy Treats": [
        "Gluten Free",
        "Contains Milk"
    ],
    "Orange Jello": [
        "Gluten Free"
    ],
    "Vegan Maple Pecan Cookie": [
        "Vegan",
        "Vegetarian",
        "Contains Tree Nuts",
        "Contains Wheat",
        "Contains Soybeans"
    ],
    "Baked Tofu": [
        "Vegan",
        "Vegetarian",
        "Gluten Free",
        "Contains Soybeans"
    ],
    "Braised Lentils": [
        "Vegan",
        "Vegetarian",
        "Gluten Free"
    ],
    "Indian Vegetable Vindaloo with Basil Sauce": [
        "Vegan",
        "Vegetarian",
        "Gluten Free"
    ],
    "Indian Chicken Vindaloo with Basil Sauce": [
        "Gluten Free"
    ],
    "Greek Flatbread": [
        "Contains Milk",
        "Contains Wheat",
        "Contains Soybeans"
    ],
    "Garlic Breadsticks": [
        "Vegetarian",
        "Contains Milk",
        "Contains Wheat"
    ],
    "Tortellini Pomodoro": [
        "Vegetarian",
        "Contains Milk",
        "Contains Eggs",
        "Contains Wheat"
    ],
    "Chocolate Whoopie": [
        "Vegetarian",
        "Contains Milk",
        "Contains Eggs",
        "Contains Wheat",
        "Contains Soybeans"
    ],
    "Vegan Raspberry Cupcakes": [
        "Contains Wheat",
        "Contains Soybeans"
    ],
    "Denver Scramble": [
        "Contains Milk",
        "Contains Eggs"
    ],
    "Cinnamon Swirl Coffee Cake": [
        "Vegetarian",
        "Contains Milk",
        "Contains Eggs",
        "Contains Wheat",
        "Contains Soybeans"
    ],
    "Thai Chicken Flat Bread Pizza": [
        "Contains Milk",
        "Contains Wheat",
        "Contains Soybeans"
    ],
    "Pizza Grilled Cheese": [
        "Contains Milk",
        "Contains Wheat"
    ],
    "Brazilian Black Beans": [
        "Vegan",
        "Vegetarian",
        "Gluten Free"
    ],
    "Fried Plantains": [
        "Vegan",
        "Vegetarian",
        "Gluten Free"
    ],
    "Green Poblano Rice": [
        "Vegan",
        "Vegetarian",
        "Gluten Free"
    ],
    "Mojo Criollo Rotisserie Halal Chicken": [
        "Gluten Free"
    ],
    "Cream Cheese Brownie": [
        "Contains Milk",
        "Contains Eggs",
        "Contains Wheat",
        "Contains Soybeans"
    ],
    "Tapioca Pudding": [
        "Contains Milk"
    ],
    "Vegan Maple Cupcake": [
        "Vegan",
        "Vegetarian",
        "Contains Wheat",
        "Contains Soybeans"
    ],
    "Roasted Corn": [
        "Vegan",
        "Vegetarian",
        "Gluten Free"
    ],
    "Vegan Smokey Tomato Sauce": [
        "Vegan",
        "Vegetarian",
        "Gluten Free",
        "Contains Soybeans"
    ],
    "Chicken Dan Dan Noodle": [
        "Contains Crustacean Shellfish",
        "Contains Wheat",
        "Contains Soybeans",
        "Contains Sesame"
    ],
    "Talya's Chicken, Shrimp and Sausage Gumbo": [
        "Contains Crustacean Shellfish",
        "Contains Wheat"
    ],
    "Chipotle Barbecue Chicken": [
        "Gluten Free"
    ],
    "Assorted Vegan and Gluten Friendly Cookies": [
        "Vegetarian",
        "Contains Wheat",
        "Contains Soybeans"
    ],
    "Chocolate Covered Macaroons": [
        "Vegetarian",
        "Contains Milk",
        "Contains Eggs",
        "Contains Wheat",
        "Contains Soybeans"
    ],
    "Banana Pancakes": [
        "Vegetarian",
        "Contains Milk",
        "Contains Eggs",
        "Contains Wheat",
        "Contains Soybeans"
    ],
    "Butter Croissant": [
        "Vegetarian",
        "Contains Milk",
        "Contains Wheat"
    ],
    "Vegan Marble Loaf Cake": [
        "Vegan",
        "Vegetarian",
        "Contains Wheat"
    ],
    "Hand Crafted Italian Pepperoni Pizza": [
        "Contains Milk",
        "Contains Wheat",
        "Contains Soybeans"
    ],
    "Cut Corn": [
        "Vegan",
        "Vegetarian",
        "Gluten Free"
    ],
    "Jerk Chicken Slider": [
        "Contains Milk",
        "Contains Wheat",
        "Contains Soybeans"
    ],
    "Basil Pesto Mac": [
        "Vegetarian",
        "Contains Milk",
        "Contains Wheat"
    ],
    "Chimichurri sauce": [
        "Vegan",
        "Vegetarian",
        "Gluten Free"
    ],
    "Herb Roasted Potatoes": [
        "Vegan",
        "Vegetarian",
        "Gluten Free"
    ],
    "Fudge Crumb Bar": [
        "Vegetarian",
        "Contains Milk",
        "Contains Eggs",
        "Contains Wheat",
        "Contains Soybeans"
    ],
    "Coconut Curry Sauce": [
        "Gluten Free",
        "Contains Tree Nuts"
    ],
    "Saffron Basmati Rice": [
        "Vegetarian",
        "Gluten Free"
    ],
    "Plantspired Dan Dan Noodle": [
        "Vegan",
        "Vegetarian",
        "Contains Wheat",
        "Contains Soybeans",
        "Contains Sesame"
    ],
    "Hand Crafted Italian Buffalo Chicken Pizza": [
        "Contains Milk",
        "Contains Eggs",
        "Contains Wheat",
        "Contains Soybeans"
    ],
    "Wild Mushroom Flatbread": [
        "Vegetarian",
        "Contains Milk",
        "Contains Wheat",
        "Contains Soybeans"
    ],
    "Cheeseburger": [
        "Contains Milk",
        "Contains Wheat",
        "Contains Soybeans"
    ],
    "Pollo Loco Halal Chicken": [
        "Gluten Free"
    ],
    "Salsa Fresca": [
        "Vegan",
        "Vegetarian",
        "Gluten Free"
    ],
    "Funfetti Cupcakes": [
        "Contains Milk",
        "Contains Eggs",
        "Contains Wheat",
        "Contains Soybeans"
    ],
    "Vegan Strawberry Lemonade Cupcake": [
        "Vegan",
        "Vegetarian",
        "Contains Wheat",
        "Contains Soybeans"
    ],
    "Crispy Shiitaki Mushrooms with Teriyaki Sauce": [
        "Contains Tree Nuts",
        "Contains Soybeans",
        "Contains Sesame"
    ],
    "Lemon Loaf": [
        "Vegetarian",
        "Contains Milk",
        "Contains Eggs",
        "Contains Wheat",
        "Contains Soybeans"
    ],
    "Vegan Blueberry Muffin": [
        "Vegan",
        "Vegetarian",
        "Contains Wheat",
        "Contains Soybeans"
    ],
    "Halal Plum Chicken Lettuce Wraps": [
        "Contains Wheat",
        "Contains Soybeans",
        "Contains Sesame"
    ],
    "Spicy Plum Ginger Tofu": [
        "Contains Wheat",
        "Contains Soybeans",
        "Contains Sesame"
    ],
    "Chicken Nuggets": [
        "Contains Wheat"
    ],
    "Vegan Nuggets": [
        "Vegan",
        "Vegetarian",
        "Contains Wheat",
        "Contains Soybeans"
    ],
    "Polynesian Chicken": [
        "Contains Soybeans"
    ],
    "Raspberry Jello": [
        "Gluten Free"
    ],
    "Red Velvet Bar": [
        "Vegetarian",
        "Contains Milk",
        "Contains Eggs",
        "Contains Wheat",
        "Contains Soybeans"
    ],
    "Vegan Chocolate Chip Cookie": [
        "Vegan",
        "Vegetarian",
        "Contains Milk",
        "Contains Wheat",
        "Contains Soybeans"
    ],
    "Green Beans": [
        "Vegan",
        "Vegetarian",
        "Gluten Free"
    ],
    "Filipino Pancit with Chicken": [
        "Contains Crustacean Shellfish",
        "Contains Wheat",
        "Contains Soybeans"
    ],
    "Filipino Pancit with Vegetables": [
        "Vegan",
        "Vegetarian",
        "Contains Soybeans"
    ],
    "Chicken and Mushroom Alfredo Pasta": [
        "Contains Milk",
        "Contains Wheat"
    ],
    "Penne Marinara": [
        "Vegetarian",
        "Contains Milk",
        "Contains Wheat"
    ],
    "Citrus Grilled Fish Tacos": [
        "Gluten Free",
        "Contains Milk",
        "Contains Eggs",
        "Contains Fish"
    ],
    "Vegan Tempeh Tacos": [
        "Vegan",
        "Vegetarian",
        "Gluten Free",
        "Contains Soybeans"
    ],
    "Chocolate Cheesecake": [
        "Contains Milk",
        "Contains Eggs",
        "Contains Soybeans"
    ],
    "Vegan Oreo Brownie": [
        "Vegan",
        "Vegetarian",
        "Contains Wheat",
        "Contains Soybeans"
    ],
    "Double Chocolate Muffin": [
        "Contains Milk",
        "Contains Eggs",
        "Contains Wheat",
        "Contains Soybeans"
    ],
    "Vegan Cranberry Muffin": [
        "Vegan",
        "Vegetarian",
        "Contains Wheat"
    ],
    "Barbeque Pulled Pork Sliders": [
        "Contains Milk",
        "Contains Wheat",
        "Contains Soybeans"
    ],
    "Vegan Barbecued Pulled Jackfruit Sandwich": [
        "Vegan",
        "Vegetarian",
        "Contains Wheat",
        "Contains Soybeans"
    ],
    "Cheddar Mashed Potatoes": [
        "Vegetarian",
        "Gluten Free",
        "Contains Milk"
    ],
    "Lemon Pudding": [
        "Vegetarian",
        "Gluten Free",
        "Contains Milk"
    ],
    "Kung Pao Peanut Chicken": [
        "Contains Peanuts",
        "Contains Soybeans",
        "Contains Sesame"
    ],
    "Kung Pao Peanut Soy Chicken": [
        "Vegetarian",
        "Contains Peanuts",
        "Contains Soybeans"
    ],
    "Pasta Marinara and Meatballs": [
        "Contains Milk",
        "Contains Wheat",
        "Contains Soybeans"
    ],
    "Matcha Panna Cotta": [
        "Gluten Free",
        "Contains Milk"
    ],
    "Marble Loaf Cake": [
        "Vegetarian",
        "Contains Milk",
        "Contains Eggs",
        "Contains Wheat",
        "Contains Soybeans"
    ],
    "Vegan Chocolate Peanut Butter Loaf": [
        "Vegan",
        "Vegetarian",
        "Contains Peanuts",
        "Contains Wheat",
        "Contains Soybeans"
    ],
    "Chicken Pozole": [],
    "Chili Cheese Dog": [
        "Contains Milk",
        "Contains Wheat"
    ],
    "Buffalo Ranch Chicken Halal": [
        "Gluten Free",
        "Contains Milk"
    ],
    "Coconut Curried Chicken": [
        "Gluten Free",
        "Contains Tree Nuts"
    ],
    "Vegan Chana Masala - India": [
        "Vegan",
        "Vegetarian",
        "Gluten Free"
    ],
    "Raspberry Chipotle BBQ Pork": [
        "Contains Milk",
        "Contains Wheat",
        "Contains Soybeans"
    ],
    "Banana Cream Pie": [
        "Vegetarian",
        "Contains Milk",
        "Contains Eggs",
        "Contains Wheat",
        "Contains Soybeans"
    ],
    "Vegan Fudge Brownie": [
        "Contains Wheat"
    ],
    "Country Scrambled": [
        "Gluten Free",
        "Contains Milk",
        "Contains Eggs"
    ],
    "Buttermilk Pancakes": [
        "Vegetarian",
        "Contains Milk",
        "Contains Eggs",
        "Contains Wheat",
        "Contains Soybeans"
    ],
    "Assorted European Mini Danish": [
        "Contains Milk",
        "Contains Eggs",
        "Contains Tree Nuts",
        "Contains Wheat",
        "Contains Soybeans"
    ],
    "Citrus Strawberry Salad": [
        "Vegetarian",
        "Gluten Free"
    ],
    "Korean BBQ Tempeh Taco": [
        "Vegan",
        "Vegetarian",
        "Contains Wheat",
        "Contains Soybeans",
        "Contains Sesame"
    ],
    "Korean Tacos with Kogi BBQ Sauce": [
        "Contains Wheat",
        "Contains Soybeans",
        "Contains Sesame"
    ],
    "Gourmet Bacon Cheese Pizza": [
        "Contains Milk",
        "Contains Wheat",
        "Contains Soybeans"
    ],
    "Cheeseburger Fries": [
        "Contains Milk",
        "Contains Eggs"
    ],
    "Fudge Brownies": [
        "Vegetarian",
        "Contains Milk",
        "Contains Eggs",
        "Contains Wheat",
        "Contains Soybeans"
    ],
    "Strawberries N' Cream Jello": [
        "Contains Milk"
    ],
    "Argentinian Halal Beef Sirloin with Chimi Churri": [
        "Gluten Free"
    ],
    "Roasted Cauliflower with Brown Butter": [
        "Vegetarian",
        "Gluten Free",
        "Contains Milk"
    ],
    "Dipped Marshmallows": [],
    "Vegan Oatmeal Raisin Cookie": [
        "Vegan",
        "Vegetarian",
        "Contains Wheat",
        "Contains Soybeans"
    ],
    "Vegan Apple Turnover": [
        "Vegan",
        "Vegetarian",
        "Contains Wheat",
        "Contains Soybeans"
    ],
    "Tikka Masala Chicken": [
        "Gluten Free",
        "Contains Milk"
    ],
    "Vegetable Tikka Masala": [
        "Vegetarian",
        "Gluten Free",
        "Contains Milk",
        "Contains Soybeans"
    ],
    "Hand Crafted Italian Veggie Supreme Pizza": [
        "Vegetarian",
        "Contains Milk",
        "Contains Wheat",
        "Contains Soybeans"
    ],
    "Chicken Strips": [
        "Contains Milk",
        "Contains Eggs",
        "Contains Wheat"
    ],
    "Vegan Breaded Chicken Strip": [
        "Vegan",
        "Vegetarian",
        "Contains Wheat",
        "Contains Soybeans"
    ],
    "Banana Pudding": [
        "Gluten Free",
        "Contains Milk"
    ],
    "Dulce de Leche Bar": [
        "Vegetarian",
        "Contains Milk",
        "Contains Eggs",
        "Contains Wheat",
        "Contains Soybeans"
    ],
    "Vegan Red Velvet Cookie": [
        "Vegan",
        "Vegetarian",
        "Contains Wheat"
    ],
    "Plant Based Beef Stir Fry": [
        "Vegetarian",
        "Contains Wheat",
        "Contains Soybeans",
        "Contains Sesame"
    ],
    "Smoked Ham on a Bavarian Pretzel Roll": [
        "Contains Milk",
        "Contains Eggs",
        "Contains Wheat",
        "Contains Soybeans"
    ],
    "Vegan Cookies N' Cream Cupcake": [
        "Vegan",
        "Vegetarian",
        "Contains Wheat",
        "Contains Soybeans"
    ],
    "White Buttercream Cake": [
        "Vegetarian",
        "Contains Milk",
        "Contains Eggs",
        "Contains Wheat",
        "Contains Soybeans"
    ]
}